.git_commit
AUTHORS
LICENSE
MANIFEST.in
README.md
VERSION
pydoop.properties
setup.cfg
setup.py
docs/html/.buildinfo
docs/html/genindex.html
docs/html/how_to_cite.html
docs/html/ideas_list.html
docs/html/index.html
docs/html/installation.html
docs/html/objects.inv
docs/html/py-modindex.html
docs/html/pydoop_script.html
docs/html/running_pydoop_applications.html
docs/html/search.html
docs/html/searchindex.js
docs/html/self_contained.html
docs/html/_sources/how_to_cite.txt
docs/html/_sources/ideas_list.txt
docs/html/_sources/index.txt
docs/html/_sources/installation.txt
docs/html/_sources/pydoop_script.txt
docs/html/_sources/running_pydoop_applications.txt
docs/html/_sources/self_contained.txt
docs/html/_sources/api_docs/hadut.txt
docs/html/_sources/api_docs/hdfs_api.txt
docs/html/_sources/api_docs/index.txt
docs/html/_sources/api_docs/mr_api.txt
docs/html/_sources/api_docs/simulator.txt
docs/html/_sources/examples/avro.txt
docs/html/_sources/examples/index.txt
docs/html/_sources/examples/input_format.txt
docs/html/_sources/examples/intro.txt
docs/html/_sources/examples/sequence_file.txt
docs/html/_sources/news/archive.txt
docs/html/_sources/news/index.txt
docs/html/_sources/news/latest.txt
docs/html/_sources/tutorial/hdfs_api.txt
docs/html/_sources/tutorial/index.txt
docs/html/_sources/tutorial/mapred_api.txt
docs/html/_sources/tutorial/pydoop_script.txt
docs/html/_static/ajax-loader.gif
docs/html/_static/basic.css
docs/html/_static/comment-bright.png
docs/html/_static/comment-close.png
docs/html/_static/comment.png
docs/html/_static/contents.png
docs/html/_static/crs4.png
docs/html/_static/doctools.js
docs/html/_static/down-pressed.png
docs/html/_static/down.png
docs/html/_static/favicon.ico
docs/html/_static/file.png
docs/html/_static/jquery.js
docs/html/_static/logo.png
docs/html/_static/minus.png
docs/html/_static/navigation.png
docs/html/_static/plus.png
docs/html/_static/pygments.css
docs/html/_static/searchtools.js
docs/html/_static/sphinxdoc.css
pydoop.egg-info/PKG-INFO
pydoop.egg-info/SOURCES.txt
pydoop.egg-info/dependency_links.txt
pydoop.egg-info/entry_points.txt
pydoop.egg-info/requires.txt
pydoop.egg-info/top_level.txt
