Metadata-Version: 1.1
Name: pydoop
Version: 1.2.0
Summary: Pydoop: a Python MapReduce and HDFS API for Hadoop
Home-page: http://crs4.github.io/pydoop
Author: Simone Leo, Gianluigi Zanetti, Luca Pireddu, Francesco Cabras, Mauro Del Rio, Marco Enrico Piras
Author-email: <simone.leo@crs4.it>, <gianluigi.zanetti@crs4.it>, <luca.pireddu@crs4.it>, <francesco.cabras@crs4.it>, <mauro@crs4.it>, <kikkomep@crs4.it>
License: Apache-2.0
Download-URL: https://pypi.python.org/pypi/pydoop
Keywords: hadoop,mapreduce
Platform: Linux
Classifier: Programming Language :: Python
Classifier: License :: OSI Approved :: Apache Software License
Classifier: Operating System :: POSIX :: Linux
Classifier: Topic :: Software Development :: Libraries :: Application Frameworks
Classifier: Intended Audience :: Developers
